{
  "sourceName": "tanzania",
  "title": "Танзания",
  "genre": "animalism",
  "author": "Kukharskiy Igor",
  "size": "70 х 70",
  "year": "2013",
  "materials": "canvas, oil",
  "description": "Igor Kukharskiy is a master of impressionism. This artpiece is done with oil on canvas. 'Tanzania' is related to impressionism being a representative of animalistic genre. ",
  "guiness": "FALSE",
  "price": "1000",
  "nftUrl": "https://opensea.io/assets/0x495f947276749ce646f68ac8c248420045cb7b5e/70889449017864859732363917643441167676610950357761192580025505611498404184065/"
}